LICENSE
README.md
setup.cfg
setup.py
HyIo/__init__.py
HyIo/debounce.py
HyIo/device.py
HyIo/gpioDevice.py
HyIo/i2cDevice.py
HyIo/ioManager.py
HyIo/parser.py
HyIo/pin.py
HyIo/test_debounce.py
HyIo/test_device.py
HyIo/test_ioManager.py
HyIo/test_parser.py
HyIo/test_pin.py
HyIo.egg-info/PKG-INFO
HyIo.egg-info/SOURCES.txt
HyIo.egg-info/dependency_links.txt
HyIo.egg-info/requires.txt
HyIo.egg-info/top_level.txt