Metadata-Version: 2.1
Name: HyIo
Version: 0.2.5
Summary: Abstraction to Io device on raspberry pi
Home-page: https://github.com/Erik-Morbach/HyIo
Download-URL: https://github.com/Erik-Morbach/HyIo/archive/refs/tags/V0.2.5.tar.gz
Author: Erik Cruz Morbach
Author-email: morbacherik@gmail.com
License: MIT
Keywords: io,raspberry,abstraction
Classifier: Development Status :: 3 - Alpha
Classifier: Intended Audience :: Developers
Classifier: Topic :: Software Development :: Build Tools
Classifier: License :: OSI Approved :: MIT License
Classifier: Programming Language :: Python :: 3.7
Classifier: Programming Language :: Python :: 3.9
Classifier: Programming Language :: Python :: 3.10
Classifier: Programming Language :: Python :: 3.11
License-File: LICENSE
